guess_file_mime_type.py
guess_file_mime_type-0.1.0a1.dist-info/licenses/LICENSE
guess_file_mime_type-0.1.0a1.dist-info/METADATA
guess_file_mime_type-0.1.0a1.dist-info/WHEEL
guess_file_mime_type-0.1.0a1.dist-info/top_level.txt
guess_file_mime_type-0.1.0a1.dist-info/RECORD
