Metadata-Version: 2.4
Name: guess-file-mime-type
Version: 0.1.0a1
Summary: A minimal, cross-platform, and cross-version utility to safely guess a file's MIME type.
Author-email: Jifeng Wu <jifengwu2k@gmail.com>
License-Expression: MIT
Project-URL: Homepage, https://github.com/jifengwu2k/guess-file-mime-type
Project-URL: Bug Tracker, https://github.com/jifengwu2k/guess-file-mime-type/issues
Classifier: Programming Language :: Python :: 2
Classifier: Programming Language :: Python :: 3
Classifier: Operating System :: OS Independent
Requires-Python: >=2
License-File: LICENSE
Dynamic: license-file
